pelican/plugins/theme_config/__init__.py
pelican/plugins/theme_config/theme_config.py
pelican_theme_config-2.0.2.dist-info/WHEEL
pelican_theme_config-2.0.2.dist-info/METADATA
pelican_theme_config-2.0.2.dist-info/RECORD
